{"id": "3881", "mmWidth": 84.0, "mmHeight": 334.0, "nbImages": 1, "nbCol": 2, "blocks": {"3822": {"coordinates": [[0.0, 72.0], [84.0, 72.0], [84.0, 80.0], [0.0, 80.0]], "xy": [0.0, 72.0], "width": 84.0, "height": 8.0, "feature": "LEGENDE"}, "29984": {"coordinates": [[0.0, 0.0], [84.0, 0.0], [84.0, 8.0], [0.0, 8.0]], "xy": [0.0, 0.0], "width": 84.0, "height": 8.0, "feature": "SURTITRE"}}, "text_block": {"id": "666", "feature": "TEXTE", "polygons": [{"outer_boundary": [[0.0, 72.0], [0.0, 12.0], [84.0, 12.0], [84.0, 72.0]], "holes": []}, {"outer_boundary": [[0.0, 334.0], [0.0, 80.0], [84.0, 80.0], [84.0, 334.0]], "holes": []}]}}